ez_cli/__init__.py
ez_cli/tasks.py
ez_cli-0.3.0.dist-info/LICENSE
ez_cli-0.3.0.dist-info/METADATA
ez_cli-0.3.0.dist-info/WHEEL
ez_cli-0.3.0.dist-info/entry_points.txt
ez_cli-0.3.0.dist-info/top_level.txt
ez_cli-0.3.0.dist-info/RECORD
