Metadata-Version: 2.1
Name: ez-cli
Version: 0.3.0
Summary: A small cli
Home-page: https://github.com/harsh376/ez-cli
Author: Harsh Verma
Author-email: harsh376@gmail.com
License: UNKNOWN
Platform: UNKNOWN
Requires-Python: >=3.7
Requires-Dist: invoke
